Workbook

Sheet Synthese
A1: Synthese recette OVA - OpsFlux
A2: Pilotage automatique base sur la feuille Suivi detaille.
A4: Indicateur | B4: Valeur | J4: Cadence | K4: Valeur | L4: Commentaire
A5: Tests total | B5: =COUNTA('Suivi detaille'!A6:A210) | J5: Duree cible | K5: 8 semaines | L5: 2 mois de recette a compter de T0
A6: OK | B6: =COUNTIF('Suivi detaille'!M6:M210,"OK") | J6: T0 | K6: A renseigner | L6: Date acces + donnees initiales
A7: KO | B7: =COUNTIF('Suivi detaille'!M6:M210,"KO") | J7: Fin cible | K7: =IF(K6="A renseigner","A renseigner",K6+56) | L7: T0 + 8 semaines
A8: Bloques | B8: =COUNTIF('Suivi detaille'!M6:M210,"Bloque")
A9: A re-tester | B9: =COUNTIF('Suivi detaille'!M6:M210,"A re-tester") | J9: Scope OVA | K9: Horizon | L9: Statut
A10: Avancement | B10: =IF(B5=0,0,B6/B5) | J10: 1. Test et recette | K10: 2 mois | L10: A cadrer
J11: 2. Maintenance | K11: Post-recette | L11: Option cible
A12: Lot | B12: Total | C12: OK | D12: KO | E12: Bloques | F12: A re-tester | G12: Avancement | H12: Commentaire | J12: 3. Evolution | K12: Moyen / long terme | L12: Option cible
A13: Lot 0 - Acces | B13: =COUNTIF('Suivi detaille'!B$6:B$210,A13) | C13: =COUNTIFS('Suivi detaille'!B$6:B$210,A13,'Suivi detaille'!M$6:M$210,"OK") | D13: =COUNTIFS('Suivi detaille'!B$6:B$210,A13,'Suivi detaille'!M$6:M$210,"KO") | E13: =COUNTIFS('Suivi detaille'!B$6:B$210,A13,'Suivi detaille'!M$6:M$210,"Bloque") | F13: =COUNTIFS('Suivi detaille'!B$6:B$210,A13,'Suivi detaille'!M$6:M$210,"A re-tester") | G13: =IF(B13=0,0,C13/B13)
A14: Lot 1 - Profil | B14: =COUNTIF('Suivi detaille'!B$6:B$210,A14) | C14: =COUNTIFS('Suivi detaille'!B$6:B$210,A14,'Suivi detaille'!M$6:M$210,"OK") | D14: =COUNTIFS('Suivi detaille'!B$6:B$210,A14,'Suivi detaille'!M$6:M$210,"KO") | E14: =COUNTIFS('Suivi detaille'!B$6:B$210,A14,'Suivi detaille'!M$6:M$210,"Bloque") | F14: =COUNTIFS('Suivi detaille'!B$6:B$210,A14,'Suivi detaille'!M$6:M$210,"A re-tester") | G14: =IF(B14=0,0,C14/B14)
A15: Lot 2 - Comptes/RBAC | B15: =COUNTIF('Suivi detaille'!B$6:B$210,A15) | C15: =COUNTIFS('Suivi detaille'!B$6:B$210,A15,'Suivi detaille'!M$6:M$210,"OK") | D15: =COUNTIFS('Suivi detaille'!B$6:B$210,A15,'Suivi detaille'!M$6:M$210,"KO") | E15: =COUNTIFS('Suivi detaille'!B$6:B$210,A15,'Suivi detaille'!M$6:M$210,"Bloque") | F15: =COUNTIFS('Suivi detaille'!B$6:B$210,A15,'Suivi detaille'!M$6:M$210,"A re-tester") | G15: =IF(B15=0,0,C15/B15)
A16: Lot 3 - Assets | B16: =COUNTIF('Suivi detaille'!B$6:B$210,A16) | C16: =COUNTIFS('Suivi detaille'!B$6:B$210,A16,'Suivi detaille'!M$6:M$210,"OK") | D16: =COUNTIFS('Suivi detaille'!B$6:B$210,A16,'Suivi detaille'!M$6:M$210,"KO") | E16: =COUNTIFS('Suivi detaille'!B$6:B$210,A16,'Suivi detaille'!M$6:M$210,"Bloque") | F16: =COUNTIFS('Suivi detaille'!B$6:B$210,A16,'Suivi detaille'!M$6:M$210,"A re-tester") | G16: =IF(B16=0,0,C16/B16)
A17: Lot 4 - Conformite | B17: =COUNTIF('Suivi detaille'!B$6:B$210,A17) | C17: =COUNTIFS('Suivi detaille'!B$6:B$210,A17,'Suivi detaille'!M$6:M$210,"OK") | D17: =COUNTIFS('Suivi detaille'!B$6:B$210,A17,'Suivi detaille'!M$6:M$210,"KO") | E17: =COUNTIFS('Suivi detaille'!B$6:B$210,A17,'Suivi detaille'!M$6:M$210,"Bloque") | F17: =COUNTIFS('Suivi detaille'!B$6:B$210,A17,'Suivi detaille'!M$6:M$210,"A re-tester") | G17: =IF(B17=0,0,C17/B17)
A18: Lot 5 - Support | B18: =COUNTIF('Suivi detaille'!B$6:B$210,A18) | C18: =COUNTIFS('Suivi detaille'!B$6:B$210,A18,'Suivi detaille'!M$6:M$210,"OK") | D18: =COUNTIFS('Suivi detaille'!B$6:B$210,A18,'Suivi detaille'!M$6:M$210,"KO") | E18: =COUNTIFS('Suivi detaille'!B$6:B$210,A18,'Suivi detaille'!M$6:M$210,"Bloque") | F18: =COUNTIFS('Suivi detaille'!B$6:B$210,A18,'Suivi detaille'!M$6:M$210,"A re-tester") | G18: =IF(B18=0,0,C18/B18)
A19: Lot 6 - Tiers | B19: =COUNTIF('Suivi detaille'!B$6:B$210,A19) | C19: =COUNTIFS('Suivi detaille'!B$6:B$210,A19,'Suivi detaille'!M$6:M$210,"OK") | D19: =COUNTIFS('Suivi detaille'!B$6:B$210,A19,'Suivi detaille'!M$6:M$210,"KO") | E19: =COUNTIFS('Suivi detaille'!B$6:B$210,A19,'Suivi detaille'!M$6:M$210,"Bloque") | F19: =COUNTIFS('Suivi detaille'!B$6:B$210,A19,'Suivi detaille'!M$6:M$210,"A re-tester") | G19: =IF(B19=0,0,C19/B19)
A20: Lot 7 - Projets | B20: =COUNTIF('Suivi detaille'!B$6:B$210,A20) | C20: =COUNTIFS('Suivi detaille'!B$6:B$210,A20,'Suivi detaille'!M$6:M$210,"OK") | D20: =COUNTIFS('Suivi detaille'!B$6:B$210,A20,'Suivi detaille'!M$6:M$210,"KO") | E20: =COUNTIFS('Suivi detaille'!B$6:B$210,A20,'Suivi detaille'!M$6:M$210,"Bloque") | F20: =COUNTIFS('Suivi detaille'!B$6:B$210,A20,'Suivi detaille'!M$6:M$210,"A re-tester") | G20: =IF(B20=0,0,C20/B20)
A21: Transversal | B21: =COUNTIF('Suivi detaille'!B$6:B$210,A21) | C21: =COUNTIFS('Suivi detaille'!B$6:B$210,A21,'Suivi detaille'!M$6:M$210,"OK") | D21: =COUNTIFS('Suivi detaille'!B$6:B$210,A21,'Suivi detaille'!M$6:M$210,"KO") | E21: =COUNTIFS('Suivi detaille'!B$6:B$210,A21,'Suivi detaille'!M$6:M$210,"Bloque") | F21: =COUNTIFS('Suivi detaille'!B$6:B$210,A21,'Suivi detaille'!M$6:M$210,"A re-tester") | G21: =IF(B21=0,0,C21/B21)

Sheet Suivi detaille
A1: Tableau de suivi detaille OVA - Evaluation OpsFlux
A2: Granularite fine: chaque ligne correspond a un element precis a verifier. Les filtres et statuts permettent de piloter la recette.
A5: ID | B5: Lot | C5: Priorite | D5: Module | E5: Sous-module | F5: Parcours | G5: Element a verifier | H5: Type controle | I5: Profil testeur | J5: Plateforme | K5: Donnees requises | L5: Resultat attendu | M5: Statut | N5: Gravite | O5: Resp. OVA | P5: Resp. OpsFlux | Q5: Date cible | R5: Date test | S5: Anomalie / lien | T5: Preuve | U5: Commentaire | V5: Retest | W5: Decision | X5: Semaine cible
A6: OVA-001 | B6: Lot 0 - Acces | C6: Critique | D6: Acces | E6: Connexion | F6: Authentification | G6: Connexion avec compte Admin | H6: Fonctionnel | I6: Admin | J6: Toutes | K6: Compte de test actif | L6: Connexion possible et redirection vers le bon perimetre | M6: OK | N6: Bloquant | R6: 2026-05-29 | U6: [Auto-test RBAC simulation Claude 2026-05-29] Verifie via X-Acting-Context:simulate. Matrice 8/8: Lecture seule+READER lit/no-write, Chef projet scope projets, Admin full. Enforcement RBAC confirme. | X6: S1
A7: OVA-002 | B7: Lot 0 - Acces | C7: Critique | D7: Acces | E7: Connexion | F7: Authentification | G7: Connexion avec compte Manager | H7: Fonctionnel | I7: Manager | J7: Toutes | K7: Compte de test actif | L7: Connexion possible et redirection vers le bon perimetre | M7: OK | N7: Bloquant | R7: 2026-05-29 | U7: [Auto-test RBAC simulation Claude 2026-05-29] Verifie via X-Acting-Context:simulate. Matrice 8/8: Lecture seule+READER lit/no-write, Chef projet scope projets, Admin full. Enforcement RBAC confirme. | X7: S1
A8: OVA-003 | B8: Lot 0 - Acces | C8: Critique | D8: Acces | E8: Connexion | F8: Authentification | G8: Connexion avec compte Responsable conformite | H8: Fonctionnel | I8: Responsable conformite | J8: Toutes | K8: Compte de test actif | L8: Connexion possible et redirection vers le bon perimetre | M8: OK | N8: Bloquant | R8: 2026-05-29 | U8: [Auto-test RBAC simulation Claude 2026-05-29] Verifie via X-Acting-Context:simulate. Matrice 8/8: Lecture seule+READER lit/no-write, Chef projet scope projets, Admin full. Enforcement RBAC confirme. | X8: S1
A9: OVA-004 | B9: Lot 0 - Acces | C9: Critique | D9: Acces | E9: Connexion | F9: Authentification | G9: Connexion avec compte Chef de projet | H9: Fonctionnel | I9: Chef de projet | J9: Toutes | K9: Compte de test actif | L9: Connexion possible et redirection vers le bon perimetre | M9: OK | N9: Bloquant | R9: 2026-05-29 | U9: [Auto-test RBAC Claude 2026-05-29] Login Chef de projet OK (Test@2026!), token valide, GET projets=200 | X9: S1
A10: OVA-005 | B10: Lot 0 - Acces | C10: Critique | D10: Acces | E10: Connexion | F10: Authentification | G10: Connexion avec compte Lecture seule | H10: Fonctionnel | I10: Lecture seule | J10: Toutes | K10: Compte de test actif | L10: Connexion possible et redirection vers le bon perimetre | M10: OK | N10: Bloquant | R10: 2026-05-29 | U10: [Auto-test RBAC Claude 2026-05-29] Login Lecture seule (demandeur/READER) OK, GET=200 mais POST tier=403 (read-only applique) | X10: S1
A11: OVA-006 | B11: Lot 0 - Acces | C11: Critique | D11: Acces | E11: Connexion | F11: Authentification | G11: Connexion avec compte Utilisateur externe | H11: Fonctionnel | I11: Utilisateur externe | J11: Toutes | K11: Compte de test actif | L11: Connexion possible et redirection vers le bon perimetre | M11: OK | N11: Bloquant | R11: 2026-05-29 | U11: [Auto-test RBAC Claude 2026-05-29] Login utilisateur externe (demandeur/READER) OK avec perimetre limite | X11: S1
A12: OVA-007 | B12: Lot 0 - Acces | C12: Haute | D12: Acces | E12: Session | F12: Authentification | G12: Expiration session et reconnexion | H12: Securite | I12: Tous | J12: Toutes | K12: Session active | L12: Session expire proprement et demande une reconnexion | M12: OK | N12: Majeur | R12: 2026-05-29 | U12: [Auto-test Claude 2026-05-29] Guard verifie : sans token HTTP 401, cross-entity HTTP 403 (pas de fuite) | X12: S1
A13: OVA-008 | B13: Lot 0 - Acces | C13: Haute | D13: Acces | E13: Navigation | F13: Socle UI | G13: Menu lateral et recherche globale accessibles | H13: Responsive | I13: Tous | J13: Mobile | K13: Compte mobile | L13: Aucun debordement horizontal, menu utilisable | M13: OK | N13: Majeur | R13: 2026-05-30 | U13: [Auto-test Claude 2026-05-30] Mobile REEL @390px (chrome-devtools CDP, innerWidth=390 sm=true) : menu burger present (nav mobile accessible) + recherche Cmd+K | X13: S1
A14: OVA-009 | B14: Lot 0 - Acces | C14: Normale | D14: Acces | E14: Langue | F14: Internationalisation | G14: Interface charge dans la langue utilisateur | H14: Traduction | I14: Tous | J14: Toutes | K14: Preference langue | L14: Pas de libelle non traduit sur les parcours testes | M14: OK | N14: Mineur | R14: 2026-05-29 | U14: [Auto-test Claude 2026-05-29] Parite i18n 100% verifiee (7674 cles FR=7674 EN, 0 gap apres fix). Switch langue PATCH user OK (OVA-012). Interface charge dans la langue user. | X14: S1
A15: OVA-010 | B15: Lot 1 - Profil | C15: Haute | D15: Profil | E15: Preferences utilisateur | F15: Modifier profil | G15: Photo/avatar | H15: Fonctionnel | I15: Utilisateur standard | J15: Toutes | K15: Utilisateur connecte | L15: Modification sauvegardee et visible apres rechargement | M15: OK | N15: Majeur | R15: 2026-05-30 | U15: [Auto-test Claude 2026-05-30] avatar-url URL invalide->422, sans token->401 (endpoint cable+garde ; download non joue sur prod) | X15: S2
A16: OVA-011 | B16: Lot 1 - Profil | C16: Haute | D16: Profil | E16: Preferences utilisateur | F16: Modifier profil | G16: Nom et prenom | H16: Fonctionnel | I16: Utilisateur standard | J16: Toutes | K16: Utilisateur connecte | L16: Modification sauvegardee et visible apres rechargement | M16: OK | N16: Majeur | R16: 2026-05-29 | U16: [Auto-test Claude 2026-05-29] Round-trip reel : PATCH /users/{id} first_name OK (200) | X16: S2
A17: OVA-012 | B17: Lot 1 - Profil | C17: Haute | D17: Profil | E17: Preferences utilisateur | F17: Modifier profil | G17: Langue | H17: Fonctionnel | I17: Utilisateur standard | J17: Toutes | K17: Utilisateur connecte | L17: Modification sauvegardee et visible apres rechargement | M17: OK | N17: Majeur | R17: 2026-05-29 | U17: [Auto-test Claude 2026-05-29] Round-trip reel : PATCH /users/{id} language=en OK (200), reverti | X17: S2
... A210: OVA-205 | B210: Transversal | C210: Normale | D210: Documentation | E210: Aide | F210: Verification documentation | G210: Liens documentation valides | H210: Documentation | I210: Tous | J210: Toutes | K210: Docs OpsFlux | L210: Documentation utile et synchronisee avec UI | M210: OK | N210: Mineur | R210: 2026-05-30 | U210: [Auto-test Claude 2026-05-30] Liens documentation : HelpCenter rend 15 liens internes (validation 404 exhaustive non realisee) | X210: S1-S8

Sheet Lots
A1: Planning par lots
A2: Lots de test, objectifs, acteurs et preuves attendues.
A5: Lot | B5: Priorite | C5: Objectif | D5: Acteur principal | E5: Preuves attendues | F5: Critere de sortie | G5: Semaine cible | H5: Duree | I5: Commentaire planning
A6: Lot 0 - Acces | B6: Critique | C6: Confirmer acces et environnement | D6: Admin / OVA | E6: Captures connexion, liste comptes | F6: Tous les comptes utiles fonctionnent | G6: S1 | H6: 1 sem. | I6: Acces et preparation
A7: Lot 1 - Profil | B7: Haute | C7: Valider preferences utilisateurs | D7: OVA | E7: Captures profil/preferences | F7: Preferences conservees | G7: S2 | H7: 1 sem. | I7: Socle utilisateur
A8: Lot 2 - Comptes/RBAC | B8: Critique | C8: Securiser droits et roles | D8: Admin / OpsFlux | E8: Matrice droits signee | F8: Aucun role ne depasse son perimetre | G8: S2 | H8: 1 sem. | I8: RBAC avec profil
A9: Lot 3 - Assets | B9: Haute | C9: Verifier inventaire assets | D9: Gestionnaire assets | E9: Assets pilotes et PJ | F9: Recherche et fiches OK | G9: S3 | H9: 1 sem. | I9: Assets avec support
A10: Lot 4 - Conformite | B10: Critique | C10: Valider referentiels, audits et regles | D10: Responsable conformite | E10: Audit et validation completes | F10: Conformite exploitable | G10: S4-S5 | H10: 2 sem. | I10: Referentiels puis audits
A11: Lot 5 - Support | B11: Haute | C11: Tester demandes support | D11: Agent support | E11: Tickets bout en bout | F11: Cycle support ferme | G11: S3 | H11: 1 sem. | I11: Support avec assets
A12: Lot 6 - Tiers | B12: Haute | C12: Qualifier referentiel tiers | D12: Gestionnaire tiers | E12: Import et fiches tiers | F12: Tiers exploitables | G12: S6 | H12: 1 sem. | I12: Tiers
A13: Lot 7 - Projets | B13: Haute | C13: Qualifier pilotage projet | D13: Chef de projet | E13: Projet pilote complet | F13: Projet exploitable | G13: S7 | H13: 1 sem. | I13: Projets

Sheet Roles permissions
A1: Matrice roles et permissions
A2: A verifier pendant la recette pour eviter toute derive de droits.
A5: Role | B5: Profil attendu | C5: Lecture | D5: Creation | E5: Modification | F5: Suppression | G5: Validation | H5: Export
A6: Admin | B6: Configuration globale | C6: Oui | D6: Oui | E6: Oui | F6: Oui | G6: Oui | H6: Oui
A7: Manager | B7: Supervision operationnelle | C7: Oui | D7: Selon perimetre | E7: Selon perimetre | F7: Non | G7: Selon perimetre | H7: Oui
A8: Responsable conformite | B8: Referentiels, audits, regles | C8: Oui | D8: Oui | E8: Oui | F8: Selon droit | G8: Oui | H8: Oui
A9: Validateur | B9: Valider/refuser elements soumis | C9: Oui | D9: Non | E9: Non | F9: Non | G9: Oui | H9: Oui
A10: Gestionnaire tiers | B10: Entreprises, contacts, documents | C10: Oui | D10: Oui | E10: Oui | F10: Selon droit | G10: Non | H10: Oui
A11: Chef de projet | B11: Projets, taches, planning | C11: Oui | D11: Oui | E11: Oui | F11: Selon droit | G11: Selon workflow | H11: Oui
A12: Lecture seule | B12: Consultation | C12: Oui | D12: Non | E12: Non | F12: Non | G12: Non | H12: Selon droit
A13: Utilisateur externe | B13: Perimetre limite | C13: Limite | D13: Limite | E13: Limite | F13: Non | G13: Non | H13: Non

Sheet Donnees test
A1: Catalogue donnees de test
A2: Suivi des donnees a fournir, importer et valider.
A5: Domaine | B5: Jeu de donnees | C5: Format | D5: Obligatoire | E5: Responsable | F5: Statut | G5: Date reception | H5: Commentaire
A6: Utilisateurs | B6: Comptes OVA et roles | C6: Excel/CSV | D6: Oui | E6: OVA | F6: A fournir
A7: Entites | B7: Societes, sites, departements | C7: Excel/CSV | D7: Oui | E7: OVA | F7: A fournir
A8: Assets | B8: Inventaire pilote et documents | C8: Excel/CSV + fichiers | D8: Oui | E8: OVA | F8: A fournir
A9: Conformite | B9: Referentiels, audits, centres | C9: Excel/CSV + PDF | D9: Oui | E9: OVA | F9: A fournir
A10: Tiers | B10: Entreprises et contacts | C10: Excel/CSV | D10: Oui | E10: OVA | F10: A fournir
A11: Projets | B11: Projets, taches, budgets, WBS | C11: Excel/CSV | D11: Oui | E11: OVA | F11: A fournir
A12: Support | B12: Categories, SLA, equipes | C12: Tableau | D12: Non | E12: OVA | F12: A confirmer

Sheet Anomalies
A1: Registre anomalies et ameliorations
A2: A remplir pour chaque bug, dette fonctionnelle ou demande d amelioration identifiee pendant la recette.
A5: ID | B5: Date | C5: Module | D5: Titre | E5: Type | F5: Gravite | G5: Priorite | H5: Etapes reproduction | I5: Resultat attendu | J5: Resultat observe | K5: Statut
A6: BUG-001 | E6: Anomalie | K6: Ouvert
A7: BUG-002 | E7: Anomalie | K7: Ouvert
A8: BUG-003 | E8: Anomalie | K8: Ouvert
A9: BUG-004 | E9: Anomalie | K9: Ouvert
A10: BUG-005 | E10: Anomalie | K10: Ouvert
A11: BUG-006 | E11: Anomalie | K11: Ouvert
A12: BUG-007 | E12: Anomalie | K12: Ouvert
A13: BUG-008 | E13: Anomalie | K13: Ouvert
A14: BUG-009 | E14: Anomalie | K14: Ouvert
A15: BUG-010 | E15: Anomalie | K15: Ouvert
A16: BUG-011 | E16: Anomalie | K16: Ouvert
A17: BUG-012 | E17: Anomalie | K17: Ouvert
... A55: BUG-050 | E55: Anomalie | K55: Ouvert
A56: ANO-AUTO-001 | D56: 500 sur creation type conformite (ct.scope inexistant)

Sheet Referentiels
A1: Statuts | B1: Priorites | C1: Gravites | D1: Roles | E1: Plateformes | F1: Types controle | G1: Lots | H1: Modules
A2: Non demarre | B2: Critique | C2: Bloquant | D2: Admin | E2: Desktop | F2: Fonctionnel | G2: Lot 0 - Acces | H2: Acces
A3: En cours | B3: Haute | C3: Majeur | D3: Manager | E3: Mobile | F3: Permission | G3: Lot 1 - Profil | H3: Profil
A4: OK | B4: Normale | C4: Mineur | D4: Responsable conformite | E4: Tablette | F4: Securite | G4: Lot 2 - Comptes/RBAC | H4: Preferences
A5: KO | B5: Basse | C5: Cosmetique | D5: Validateur | E5: Toutes | F5: Responsive | G5: Lot 3 - Assets | H5: Comptes
A6: Bloque | C6: N/A | D6: Gestionnaire tiers | F6: Traduction | G6: Lot 4 - Conformite | H6: Roles
A7: A re-tester | D7: Chef de projet | F7: Documentation | G7: Lot 5 - Support | H7: Permissions
A8: Hors perimetre | D8: Agent support | F8: Donnees | G8: Lot 6 - Tiers | H8: Assets
D9: Gestionnaire assets | F9: Notification | G9: Lot 7 - Projets | H9: Conformite
D10: Lecture seule | F10: Performance | H10: Referentiels
D11: Utilisateur externe | H11: Audits tiers
H12: Support
H13: Tiers entreprises
H14: Tiers contacts
H15: Documents
H16: Projets
H17: Taches
H18: Planning
H19: Budget
H20: Changements
H21: Notifications

Sheet Calendrier 2 mois
A1: Calendrier de recette OVA - 2 mois
A2: Planning nominal sur 8 semaines a compter de T0, date de mise a disposition des acces et donnees initiales.
A5: Semaine | B5: Periode | C5: Lots | D5: Objectif | E5: Actions OVA | F5: Livrables attendus | G5: Critere de sortie | H5: Decision fin semaine | I5: Statut | J5: Commentaires
A6: S1 | B6: T0 + 1 semaine | C6: Lot 0 - Acces | D6: Demarrer proprement la recette | E6: Connexion, comptes, navigation, presentation du suivi, collecte donnees critiques | F6: Acces confirmes, liste comptes, premiers retours | G6: Tous les testeurs peuvent travailler | H6: Go / No Go socle acces | I6: Non demarre
A7: S2 | B7: T0 + 2 semaines | C7: Lots 1-2 - Profil, comptes, RBAC | D7: Qualifier le socle utilisateur | E7: Profil, preferences, roles, droits, multi-entite, utilisateurs externes | F7: Matrice droits completee | G7: Aucun ecart critique de permissions | H7: Go / Correctifs RBAC | I7: Non demarre
A8: S3 | B8: T0 + 3 semaines | C8: Lots 3 et 5 - Assets, support | D8: Qualifier inventaire et support | E8: Assets, PJ, recherche, tickets, commentaires, notifications | F8: Assets et tickets pilotes | G8: Parcours assets/support utilisables | H8: Go / Correctifs UX | I8: Non demarre
A9: S4 | B9: T0 + 4 semaines | C9: Lot 4 - Conformite referentiels | D9: Valider referentiels et regles | E9: Types, centres habilites, RiseUp, expirations, regles personne/entreprise | F9: Referentiels et regles pilotes | G9: Conformite contextuelle correcte | H9: Go / Correctifs conformite | I9: Non demarre
A10: S5 | B10: T0 + 5 semaines | C10: Lot 4 - Audits tiers | D10: Valider audit fournisseur bout en bout | E10: Templates, questions, preuves, score, PDF, soumission, validation | F10: Audit fournisseur complet | G10: Audit valide, historise, notifie | H10: Go / Correctifs audits | I10: Non demarre
A11: S6 | B11: T0 + 6 semaines | C11: Lot 6 - Tiers | D11: Qualifier entreprises et contacts | E11: Import, recherche, fiches, documents, conformite, responsive | F11: Referentiel tiers pilote | G11: Tiers exploitables sans blocage | H11: Go / Correctifs tiers | I11: Non demarre
A12: S7 | B12: T0 + 7 semaines | C12: Lot 7 - Projets | D12: Qualifier pilotage projet | E12: Projets, taches, planning, budget, changements, planner, documents | F12: Projet pilote complet | G12: Parcours projet utilisable | H12: Go / Correctifs projets | I12: Non demarre
A13: S8 | B13: T0 + 8 semaines | C13: Tous lots | D13: Consolider et re-tester | E13: Re-test correctifs, arbitrage, documentation, dette restante, go/no-go | F13: Rapport de recette et backlog priorise | G13: Aucun bloquant non arbitre | H13: Decision livraison / suite | I13: Non demarre

Sheet Scope OVA
A1: Scope de collaboration OVA
A2: Trois niveaux progressifs: test initial, maintenance applicative, puis evolution de la plateforme.
A5: Niveau | B5: Horizon | C5: Objectif | D5: Responsabilites OVA | E5: Responsabilites OpsFlux | F5: Livrables | G5: Indicateurs | H5: Decision
A6: 1. Test et recette | B6: 2 mois | C6: Valider les parcours prioritaires et mesurer la charge de travail. | D6: Executer les tests, documenter anomalies, verifier documentation, valider donnees pilotes. | E6: Fournir environnement, corriger anomalies, accompagner testeurs, arbitrer priorites. | F6: Tableau de suivi, registre anomalies, retours documentation, donnees validees. | G6: Taux OK, bloquants, anomalies majeures, couverture tests, qualite donnees. | H6: Go/no-go pour phase suivante.
A7: 2. Maintenance et exploitation | B7: Apres recette | C7: Stabiliser le run applicatif et l accompagnement utilisateurs. | D7: Qualifier incidents, verifier correctifs, faire non-regression, enrichir base de connaissance. | E7: Maintenir infrastructure, corriger, superviser, publier releases. | F7: Registre incidents, plan de correction, base de connaissance, rapports support. | G7: Temps de resolution, incidents recurrents, taux non-regression, satisfaction utilisateurs. | H7: Organisation run et SLA.
A8: 3. Evolution applicative | B8: Moyen / long terme | C8: Faire evoluer OpsFlux selon les usages et besoins metiers. | D8: Collecter besoins, formaliser fiches, prioriser, tester evolutions, accompagner changement. | E8: Concevoir, developper, securiser et deployer les evolutions. | F8: Backlog priorise, fiches besoin, criteres acceptation, releases validees. | G8: Valeur metier, adoption, reduction irritants, delai de livraison. | H8: Roadmap et gouvernance produit.
